mwaah/__init__.py
mwaah/model.py
mwaah/mwaah.py
mwaah-0.1.1.dist-info/AUTHORS.rst
mwaah-0.1.1.dist-info/LICENSE
mwaah-0.1.1.dist-info/METADATA
mwaah-0.1.1.dist-info/WHEEL
mwaah-0.1.1.dist-info/top_level.txt
mwaah-0.1.1.dist-info/RECORD
