Metadata-Version: 2.1
Name: mwaah
Version: 0.1.1
Summary: Python Client for Apache CLI on AWS Managed Airflow
Author-email: Gregory Wiltshire <mellon.greg@gmail.com>
License: MIT
Project-URL: Homepage, https://github.com/GregoryWiltshire/mwaah
Classifier: Programming Language :: Python :: 3.7
Classifier: Programming Language :: Python :: 3.8
Classifier: Programming Language :: Python :: 3.9
Classifier: Programming Language :: Python :: 3.10
Classifier: License :: OSI Approved :: MIT License
Classifier: Operating System :: OS Independent
Requires-Python: >=3.7
License-File: LICENSE
License-File: AUTHORS.rst
Requires-Dist: apache-airflow-client
Requires-Dist: botocore (>=1.20.0)
Requires-Dist: boto3
Requires-Dist: requests
Requires-Dist: pydantic
Provides-Extra: socks
Requires-Dist: PySocks (!=1.5.7,>=1.5.6) ; extra == 'socks'
